spire/__init__.py
spire/pdf/ArtifactPropertyList.py
spire/pdf/AspectRatio.py
spire/pdf/BookletOptions.py
spire/pdf/Clip.py
spire/pdf/Collections_PdfCollection.py
spire/pdf/CompressionLevel.py
spire/pdf/ConfiguerGraphicType.py
spire/pdf/CustomFieldType.py
spire/pdf/DataFormat.py
spire/pdf/DocxOptions.py
spire/pdf/FileFormat.py
spire/pdf/FileRelatedFieldType.py
spire/pdf/Find_TextFindParameter.py
spire/pdf/GraphicMode.py
spire/pdf/HtmlConverter.py
spire/pdf/HtmlToPdfLayoutParams.py
spire/pdf/HtmlToPdfResult.py
spire/pdf/HttpMethod.py
spire/pdf/HttpReadType.py
spire/pdf/IOCSPService.py
spire/pdf/IPdfComboBoxField.py
spire/pdf/IPdfSignatureAppearance.py
spire/pdf/IPdfSignatureFormatter.py
spire/pdf/IPdfTextBoxField.py
spire/pdf/IStructureNode.py
spire/pdf/ITSAService.py
spire/pdf/ImageFormatType.py
spire/pdf/ImageQuality.py
spire/pdf/ImageType.py
spire/pdf/ImgData.py
spire/pdf/LayerExportState.py
spire/pdf/LayerPrintState.py
spire/pdf/LayerViewState.py
spire/pdf/LineBorder.py
spire/pdf/LineInfo.py
spire/pdf/LineType.py
spire/pdf/LoadHtmlType.py
spire/pdf/MergerOptions.py
spire/pdf/OCSPHttpService.py
spire/pdf/OfdConverter.py
spire/pdf/OptimizationOptions.py
spire/pdf/PDF3DAnimationType.py
spire/pdf/Pdf3DActivation.py
spire/pdf/Pdf3DActivationMode.py
spire/pdf/Pdf3DActivationState.py
spire/pdf/Pdf3DAnimation.py
spire/pdf/Pdf3DAnnotation.py
spire/pdf/Pdf3DBackground.py
spire/pdf/Pdf3DCrossSection.py
spire/pdf/Pdf3DCrossSectionCollection.py
spire/pdf/Pdf3DDeactivationMode.py
spire/pdf/Pdf3DDeactivationState.py
spire/pdf/Pdf3DLighting.py
spire/pdf/Pdf3DLightingStyle.py
spire/pdf/Pdf3DNode.py
spire/pdf/Pdf3DNodeCollection.py
spire/pdf/Pdf3DProjection.py
spire/pdf/Pdf3DProjectionClipStyle.py
spire/pdf/Pdf3DProjectionOrthoScaleMode.py
spire/pdf/Pdf3DProjectionType.py
spire/pdf/Pdf3DRenderStyle.py
spire/pdf/Pdf3DRendermode.py
spire/pdf/Pdf3DView.py
spire/pdf/Pdf3DViewCollection.py
spire/pdf/PdfAction.py
spire/pdf/PdfActionAnnotation.py
spire/pdf/PdfActionCollection.py
Spire.Pdf.Free-10.12.0.dist-info/METADATA
Spire.Pdf.Free-10.12.0.dist-info/WHEEL
Spire.Pdf.Free-10.12.0.dist-info/top_level.txt
Spire.Pdf.Free-10.12.0.dist-info/RECORD
